mace_inference/__init__.py
mace_inference/cli.py
mace_inference/core.py
mace_inference/py.typed
mace_inference/types.py
mace_inference/tasks/__init__.py
mace_inference/tasks/adsorption.py
mace_inference/tasks/dynamics.py
mace_inference/tasks/mechanics.py
mace_inference/tasks/phonon.py
mace_inference/tasks/static.py
mace_inference/utils/__init__.py
mace_inference/utils/d3_correction.py
mace_inference/utils/device.py
mace_inference/utils/io.py
mace_inference-0.1.0.dist-info/licenses/LICENSE
mace_inference-0.1.0.dist-info/METADATA
mace_inference-0.1.0.dist-info/WHEEL
mace_inference-0.1.0.dist-info/entry_points.txt
mace_inference-0.1.0.dist-info/top_level.txt
mace_inference-0.1.0.dist-info/RECORD
