Metadata-Version: 2.4
Name: mace-inference
Version: 0.1.0
Summary: High-level Python library for MACE machine learning force field inference tasks
Author-email: Shibo Li <shadow.li981@gmail.com>
Maintainer-email: Shibo Li <shadow.li981@gmail.com>
License: MIT
Project-URL: Homepage, https://github.com/lichman0405/mace-inference
Project-URL: Documentation, https://lichman0405.github.io/mace-inference/
Project-URL: Repository, https://github.com/lichman0405/mace-inference
Project-URL: Issues, https://github.com/lichman0405/mace-inference/issues
Keywords: machine learning,force field,molecular dynamics,materials science,MACE
Classifier: Development Status :: 3 - Alpha
Classifier: Intended Audience :: Science/Research
Classifier: License :: OSI Approved :: MIT License
Classifier: Programming Language :: Python :: 3
Classifier: Programming Language :: Python :: 3.9
Classifier: Programming Language :: Python :: 3.10
Classifier: Programming Language :: Python :: 3.11
Classifier: Programming Language :: Python :: 3.12
Classifier: Topic :: Scientific/Engineering :: Chemistry
Classifier: Topic :: Scientific/Engineering :: Physics
Classifier: Typing :: Typed
Requires-Python: >=3.9
License-File: LICENSE
Requires-Dist: mace-torch>=0.3.10
Requires-Dist: ase>=3.22.0
Requires-Dist: phonopy>=2.20.0
Requires-Dist: numpy>=1.20.0
Requires-Dist: click>=8.0.0
Provides-Extra: d3
Requires-Dist: torch-dftd>=0.4.0; extra == "d3"
Provides-Extra: gpu
Requires-Dist: torch<2.4.0,>=2.3.0; extra == "gpu"
Provides-Extra: dev
Requires-Dist: pytest>=7.0.0; extra == "dev"
Requires-Dist: pytest-cov>=3.0.0; extra == "dev"
Requires-Dist: ruff>=0.1.0; extra == "dev"
Requires-Dist: mypy>=0.950; extra == "dev"
Provides-Extra: docs
Requires-Dist: mkdocs-material>=9.0.0; extra == "docs"
Requires-Dist: mkdocstrings[python]>=0.24.0; extra == "docs"
Requires-Dist: mkdocs-gen-files>=0.5.0; extra == "docs"
Requires-Dist: mkdocs-literate-nav>=0.6.0; extra == "docs"
Provides-Extra: all
Requires-Dist: mace-inference[d3,dev,docs,gpu]; extra == "all"
Dynamic: license-file
